aponyx/__init__.py
aponyx/main.py
aponyx/py.typed
aponyx/backtest/__init__.py
aponyx/backtest/adapters.py
aponyx/backtest/calculator_factory.py
aponyx/backtest/calculators.py
aponyx/backtest/config.py
aponyx/backtest/engine.py
aponyx/backtest/protocols.py
aponyx/backtest/registry.py
aponyx/backtest/strategy_catalog.json
aponyx/catalog/__init__.py
aponyx/catalog/data.py
aponyx/catalog/entries.py
aponyx/catalog/loader.py
aponyx/catalog/manager.py
aponyx/catalog/migration.py
aponyx/catalog/sync.py
aponyx/catalog/sync_types.py
aponyx/catalog/validation_types.py
aponyx/catalog/validator.py
aponyx/cli/__init__.py
aponyx/cli/main.py
aponyx/cli/commands/__init__.py
aponyx/cli/commands/catalog.py
aponyx/cli/commands/clean.py
aponyx/cli/commands/list.py
aponyx/cli/commands/report.py
aponyx/cli/commands/run.py
aponyx/cli/commands/sweep.py
aponyx/config/__init__.py
aponyx/data/__init__.py
aponyx/data/bloomberg_config.py
aponyx/data/bloomberg_instruments.json
aponyx/data/bloomberg_securities.json
aponyx/data/cache.py
aponyx/data/channels.py
aponyx/data/fetch.py
aponyx/data/loaders.py
aponyx/data/registry.py
aponyx/data/requirements.py
aponyx/data/sample_data.py
aponyx/data/schemas.py
aponyx/data/security_catalog.py
aponyx/data/sources.py
aponyx/data/synthetic_params.json
aponyx/data/test_scenarios.py
aponyx/data/transforms.py
aponyx/data/validation.py
aponyx/data/providers/__init__.py
aponyx/data/providers/bloomberg.py
aponyx/data/providers/file.py
aponyx/docs/__init__.py
aponyx/docs/adding_data_providers.md
aponyx/docs/cdx_knowledge_base.md
aponyx/docs/cdx_overlay_strategy.md
aponyx/docs/cli_guide.md
aponyx/docs/governance_design.md
aponyx/docs/logging_design.md
aponyx/docs/performance_evaluation_design.md
aponyx/docs/python_guidelines.md
aponyx/docs/signal_registry_usage.md
aponyx/docs/signal_suitability_design.md
aponyx/docs/visualization_design.md
aponyx/evaluation/__init__.py
aponyx/evaluation/performance/__init__.py
aponyx/evaluation/performance/adapters.py
aponyx-0.1.22.dist-info/METADATA
aponyx-0.1.22.dist-info/WHEEL
aponyx-0.1.22.dist-info/entry_points.txt
aponyx-0.1.22.dist-info/licenses/LICENSE
aponyx-0.1.22.dist-info/RECORD
