Metadata-Version: 2.4
Name: aponyx
Version: 0.1.22
Summary: Early-stage research framework for backtesting systematic credit strategies (not for production use)
Project-URL: Homepage, https://github.com/stabilefrisur/aponyx
Project-URL: Repository, https://github.com/stabilefrisur/aponyx
Project-URL: Documentation, https://github.com/stabilefrisur/aponyx/blob/master/README.md
Project-URL: Issues, https://github.com/stabilefrisur/aponyx/issues
Project-URL: Changelog, https://github.com/stabilefrisur/aponyx/blob/master/CHANGELOG.md
Author-email: Stabile Frisur <26568863+stabilefrisur@users.noreply.github.com>
License: MIT License
License-File: LICENSE
Keywords: backtesting,finance,investing,research
Classifier: Development Status :: 3 - Alpha
Classifier: Intended Audience :: Science/Research
Classifier: License :: OSI Approved :: MIT License
Classifier: Programming Language :: Python :: 3
Classifier: Programming Language :: Python :: 3.12
Classifier: Topic :: Office/Business :: Financial :: Investment
Classifier: Typing :: Typed
Requires-Python: <3.13,>=3.12
Requires-Dist: click>=8.1.0
Requires-Dist: ipython>=8.0.0
Requires-Dist: numpy>=1.24.0
Requires-Dist: pandas>=2.0.0
Requires-Dist: pyarrow>=12.0.0
Requires-Dist: pyyaml>=6.0
Requires-Dist: quantstats>=0.0.77
Requires-Dist: ruamel-yaml>=0.18.0
Requires-Dist: scipy>=1.7.0
Requires-Dist: statsmodels>=0.14.0
Requires-Dist: tqdm>=4.67.1
Provides-Extra: bloomberg
Requires-Dist: xbbg>=0.7.0; extra == 'bloomberg'
Provides-Extra: dev
Requires-Dist: mypy>=1.19.0; extra == 'dev'
Requires-Dist: pytest-cov>=5.0.0; extra == 'dev'
Requires-Dist: pytest>=8.0.0; extra == 'dev'
Requires-Dist: ruff>=0.1.0; extra == 'dev'
Provides-Extra: viz
Requires-Dist: plotly>=5.24.0; extra == 'viz'
